odoo/addons/l10n_es_aeat_partner_check/README.rst
odoo/addons/l10n_es_aeat_partner_check/__init__.py
odoo/addons/l10n_es_aeat_partner_check/__manifest__.py
odoo/addons/l10n_es_aeat_partner_check/i18n/ca.po
odoo/addons/l10n_es_aeat_partner_check/i18n/es.po
odoo/addons/l10n_es_aeat_partner_check/i18n/l10n_es_aeat_partner_check.pot
odoo/addons/l10n_es_aeat_partner_check/models/__init__.py
odoo/addons/l10n_es_aeat_partner_check/models/res_company.py
odoo/addons/l10n_es_aeat_partner_check/models/res_config_settings.py
odoo/addons/l10n_es_aeat_partner_check/models/res_partner.py
odoo/addons/l10n_es_aeat_partner_check/readme/CONTRIBUTORS.rst
odoo/addons/l10n_es_aeat_partner_check/readme/DESCRIPTION.rst
odoo/addons/l10n_es_aeat_partner_check/readme/INSTALL.rst
odoo/addons/l10n_es_aeat_partner_check/readme/USAGE.rst
odoo/addons/l10n_es_aeat_partner_check/static/description/icon.png
odoo/addons/l10n_es_aeat_partner_check/static/description/index.html
odoo/addons/l10n_es_aeat_partner_check/tests/__init__.py
odoo/addons/l10n_es_aeat_partner_check/tests/test_res_partner.py
odoo/addons/l10n_es_aeat_partner_check/views/res_company_view.xml
odoo/addons/l10n_es_aeat_partner_check/views/res_config_settings_view.xml
odoo/addons/l10n_es_aeat_partner_check/views/res_partner_view.xml
odoo14_addon_l10n_es_aeat_partner_check-14.0.1.3.0.dist-info/METADATA
odoo14_addon_l10n_es_aeat_partner_check-14.0.1.3.0.dist-info/WHEEL
odoo14_addon_l10n_es_aeat_partner_check-14.0.1.3.0.dist-info/top_level.txt
odoo14_addon_l10n_es_aeat_partner_check-14.0.1.3.0.dist-info/RECORD
